myproject4/__init__.py
myproject4/_version.py
myproject4/skeleton.py
myproject4-0.2.0.dist-info/DESCRIPTION.rst
myproject4-0.2.0.dist-info/METADATA
myproject4-0.2.0.dist-info/RECORD
myproject4-0.2.0.dist-info/WHEEL
myproject4-0.2.0.dist-info/entry_points.txt
myproject4-0.2.0.dist-info/metadata.json
myproject4-0.2.0.dist-info/top_level.txt
