Metadata-Version: 2.0
Name: myproject4
Version: 0.2.0
Summary: Add a short description here!
Home-page: http://...
Author: rksin8
Author-email: ranjeetbhu88@gmail.com
License: mit
Platform: any
Classifier: Development Status :: 4 - Beta
Classifier: Programming Language :: Python
